citationhelper/__init__.py
citationhelper/citationhelper.py
tests/__init__.py
tests/test_citationhelper.py
citationhelper-0.4.dist-info/LICENSE
citationhelper-0.4.dist-info/METADATA
citationhelper-0.4.dist-info/WHEEL
citationhelper-0.4.dist-info/entry_points.txt
citationhelper-0.4.dist-info/top_level.txt
citationhelper-0.4.dist-info/RECORD
