Metadata-Version: 2.1
Name: citationhelper
Version: 0.4
Summary: Tool for determining packages used in a particular project that should be cited.
Home-page: UNKNOWN
Author: InGeO
Author-email: ingeo-team@ingeo.datatransport.org
License: UNKNOWN
Platform: UNKNOWN
Classifier: Development Status :: 5 - Production/Stable
Classifier: Topic :: Scientific/Engineering
Classifier: Intended Audience :: Science/Research
Classifier: License :: OSI Approved :: GNU General Public License (GPL)
Classifier: Natural Language :: English
Classifier: Programming Language :: Python
License-File: LICENSE
